upsidedown.py
upsidedown-0.4.dist-info/COPYING
upsidedown-0.4.dist-info/METADATA
upsidedown-0.4.dist-info/WHEEL
upsidedown-0.4.dist-info/entry_points.txt
upsidedown-0.4.dist-info/top_level.txt
upsidedown-0.4.dist-info/RECORD
