Metadata-Version: 2.1
Name: upsidedown
Version: 0.4
Summary: "Flip" characters in a string to create an "upside-down" impression.
Home-page: http://github.com/cburgmer/upsidedown
Author: Christoph Burgmer
Author-email: christoph.burgmer@gmail.com
License: MIT
Download-URL: http://github.com/cburgmer/upsidedown/downloads
Platform: UNKNOWN
Classifier: Environment :: Console
Classifier: Intended Audience :: Developers
Classifier: Development Status :: 5 - Production/Stable
Classifier: Operating System :: OS Independent
Classifier: Programming Language :: Python :: 2.6
Classifier: Programming Language :: Python :: 2.7
Classifier: Programming Language :: Python :: 3
Classifier: License :: OSI Approved :: MIT License
Classifier: Topic :: Text Processing
